pedurma/__init__.py
pedurma/config.py
pedurma/docx_serializer.py
pedurma/exceptions.py
pedurma/nalanda_text.py
pedurma/notes.py
pedurma/pagination_update.py
pedurma/pecha.py
pedurma/preprocess.py
pedurma/preview.py
pedurma/preview_note_layer.py
pedurma/proofreading.py
pedurma/reconstruction.py
pedurma/reinsertion.py
pedurma/save_text.py
pedurma/text_report.py
pedurma/texts.py
pedurma/utils.py
pedurma-0.1.109.dist-info/LICENSE
pedurma-0.1.109.dist-info/METADATA
pedurma-0.1.109.dist-info/WHEEL
pedurma-0.1.109.dist-info/top_level.txt
pedurma-0.1.109.dist-info/RECORD
