Metadata-Version: 2.1
Name: pedurma
Version: 0.1.109
Summary: Pedurma Reconstruction functionalities
Home-page: https://github.com/Esukhia/pedurma
Author: Ngawang Thrinley, Tenzin, Tenzin Kaldan
Author-email: esukhiadev@gmail.com
License: Apache2
Classifier: Programming Language :: Python :: 3
Classifier: License :: OSI Approved :: MIT License
Classifier: Operating System :: OS Independent
Requires-Python: >=3.8
License-File: LICENSE
Requires-Dist: antx (<1.0,>=0.1.8)
Requires-Dist: openpecha[transifex] (<1.0,>=0.7.58)
Requires-Dist: pypandoc (<2.0,>=1.7.2)
Requires-Dist: pylibyaml (<1.0,>=0.1.0)
Requires-Dist: python-docx (<9.0,>=0.8.11)
